kogia/core/__init__.py
kogia/core/apps.py
kogia/core/models.py
kogia/core/locale/en/LC_MESSAGES/django.mo
kogia/core/locale/en/LC_MESSAGES/django.po
kogia/core/locale/fr/LC_MESSAGES/django.mo
kogia/core/locale/fr/LC_MESSAGES/django.po
kogia/core/tests/__init__.py
kogia/core/tests/models.py
kogia/core/tests/test_models.py
kogia/intl/__init__.py
kogia/intl/apps.py
kogia/intl/models.py
kogia/intl/locale/en/LC_MESSAGES/django.mo
kogia/intl/locale/en/LC_MESSAGES/django.po
kogia/intl/locale/fr/LC_MESSAGES/django.mo
kogia/intl/locale/fr/LC_MESSAGES/django.po
kogia/intl/tests/__init__.py
kogia/intl/tests/models.py
kogia/intl/tests/test_models.py
kogia/pages/__init__.py
kogia/pages/apps.py
kogia/pages/models.py
kogia/pages/views.py
kogia/pages/locale/en/LC_MESSAGES/django.mo
kogia/pages/locale/en/LC_MESSAGES/django.po
kogia/pages/locale/fr/LC_MESSAGES/django.mo
kogia/pages/locale/fr/LC_MESSAGES/django.po
kogia/pages/templates/pages/page_detail.html
kogia/pages/templates/pages/page_list.html
kogia/pages/tests/__init__.py
kogia/pages/tests/models.py
kogia/pages/tests/test_models.py
kogia/pages/tests/test_views.py
kogia/pages/tests/urls.py
kogia/pages/tests/views.py
kogia-0.1.0.dev2.dist-info/LICENSE
kogia-0.1.0.dev2.dist-info/METADATA
kogia-0.1.0.dev2.dist-info/NOTICE
kogia-0.1.0.dev2.dist-info/WHEEL
kogia-0.1.0.dev2.dist-info/top_level.txt
kogia-0.1.0.dev2.dist-info/RECORD
