Metadata-Version: 2.1
Name: kogia
Version: 0.1.0.dev2
Summary: Django toolbox.
Home-page: https://kogia.pascalpepe.com
Author: Pascal Pepe
Author-email: contact@pascalpepe.com
License: Apache-2.0
Project-URL: Documentation, https://pascalpepe.gitlab.io/kogia
Project-URL: Source code, https://gitlab.com/pascalpepe/kogia
Project-URL: Issue tracker, https://gitlab.com/pascalpepe/kogia/issues
Keywords: django kogia
Platform: UNKNOWN
Classifier: Development Status :: 1 - Planning
Classifier: Environment :: Web Environment
Classifier: Framework :: Django
Classifier: Framework :: Django :: 2.2
Classifier: Framework :: Django :: 3.1
Classifier: Intended Audience :: Developers
Classifier: License :: OSI Approved :: Apache Software License
Classifier: Operating System :: OS Independent
Classifier: Programming Language :: Python
Classifier: Programming Language :: Python :: 3
Classifier: Programming Language :: Python :: 3 :: Only
Classifier: Programming Language :: Python :: 3.5
Classifier: Programming Language :: Python :: 3.6
Classifier: Programming Language :: Python :: 3.7
Classifier: Programming Language :: Python :: 3.8
Classifier: Topic :: Internet
Classifier: Topic :: Internet :: WWW/HTTP
Classifier: Topic :: Internet :: WWW/HTTP :: Dynamic Content
